nowyou_grafis_script_python/__init__.py
nowyou_grafis_script_python/start.py
nowyou_grafis_script_python/static/1a.png
nowyou_grafis_script_python/static/1b.png
nowyou_grafis_script_python/static/1c.png
nowyou_grafis_script_python/static/1ci.png
nowyou_grafis_script_python/static/2a.png
nowyou_grafis_script_python/static/2b.png
nowyou_grafis_script_python/static/2ci.png
nowyou_grafis_script_python/static/2cii.png
nowyou_grafis_script_python/static/2ciii.png
nowyou_grafis_script_python/static/2civ.png
nowyou_grafis_script_python/static/2cv.png
nowyou_grafis_script_python/static/2cvi.png
nowyou_grafis_script_python/static/2cvii.png
nowyou_grafis_script_python/static/2cviii.png
nowyou_grafis_script_python/static/2e.png
nowyou_grafis_script_python/static/3ai.png
nowyou_grafis_script_python/static/3aii.png
nowyou_grafis_script_python/static/3aiii.png
nowyou_grafis_script_python/static/3aiv.png
nowyou_grafis_script_python/static/3aix.png
nowyou_grafis_script_python/static/3av.png
nowyou_grafis_script_python/static/3avii.png
nowyou_grafis_script_python/static/3aviii.png
nowyou_grafis_script_python/static/3axii.png
nowyou_grafis_script_python/static/3bii.png
nowyou_grafis_script_python/static/3biii.png
nowyou_grafis_script_python/static/3biv.png
nowyou_grafis_script_python/static/3bvii.png
nowyou_grafis_script_python/static/4a.png
nowyou_grafis_script_python/static/4b.png
nowyou_grafis_script_python/static/5ai.png
nowyou_grafis_script_python/static/5aii.png
nowyou_grafis_script_python/static/5aiv.png
nowyou_grafis_script_python/static/5av.png
nowyou_grafis_script_python/static/__init__.py
nowyou_grafis_script_python/tasks/__init__.py
nowyou_grafis_script_python/tasks/grading.py
nowyou_grafis_script_python/tasks/launch.py
nowyou_grafis_script_python/tasks/open_project.py
nowyou_grafis_script_python/tasks/project.py
nowyou_grafis_script_python/ui_tools/UI_tools.py
nowyou_grafis_script_python/ui_tools/__init__.py
nowyou_grafis_script_python/utils/__init__.py
nowyou_grafis_script_python-1.1.41.dist-info/METADATA
nowyou_grafis_script_python-1.1.41.dist-info/WHEEL
nowyou_grafis_script_python-1.1.41.dist-info/top_level.txt
nowyou_grafis_script_python-1.1.41.dist-info/RECORD
